{
  "asOf": "2026-02-12T11:09:01.628Z",
  "entryDate": "2026-02-11",
  "source": "stooq",
  "quotes": {
    "AGI": {
      "symbol": "AGI.US",
      "entryDate": "2026-02-11",
      "entryOpen": 46.45,
      "last": null,
      "quoteDate": null,
      "quoteTime": null
    },
    "FSM": {
      "symbol": "FSM.US",
      "entryDate": "2026-02-11",
      "entryOpen": 11.5,
      "last": null,
      "quoteDate": null,
      "quoteTime": null
    },
    "GAU": {
      "symbol": "GAU.US",
      "entryDate": "2026-02-11",
      "entryOpen": 3.05,
      "last": null,
      "quoteDate": null,
      "quoteTime": null
    },
    "NFGC": {
      "symbol": "NFGC.US",
      "entryDate": "2026-02-11",
      "entryOpen": 3.1299,
      "last": null,
      "quoteDate": null,
      "quoteTime": null
    },
    "VGZ": {
      "symbol": "VGZ.US",
      "entryDate": "2026-02-11",
      "entryOpen": 3.03,
      "last": null,
      "quoteDate": null,
      "quoteTime": null
    },
    "NEWP": {
      "symbol": "NEWP.US",
      "entryDate": "2026-02-11",
      "entryOpen": 3.9,
      "last": null,
      "quoteDate": null,
      "quoteTime": null
    }
  }
}