{
  "asOf": "2026-06-18T10:45:44.108244+00:00",
  "source": "yahoo",
  "items": [
    {
      "sym": "FTSE 100",
      "value": "10,405.6",
      "change": "-0.98%",
      "dir": "neg"
    },
    {
      "sym": "S&P 500",
      "value": "7,420.1",
      "change": "-1.21%",
      "dir": "neg"
    },
    {
      "sym": "NASDAQ 100",
      "value": "29,670.9",
      "change": "-0.99%",
      "dir": "neg"
    },
    {
      "sym": "DXY",
      "value": "100.68",
      "change": "+0.59%",
      "dir": "pos"
    },
    {
      "sym": "GBP/USD",
      "value": "1.3232",
      "change": "-1.45%",
      "dir": "neg"
    },
    {
      "sym": "EUR/USD",
      "value": "1.1467",
      "change": "-1.23%",
      "dir": "neg"
    },
    {
      "sym": "BRENT",
      "value": "$78.39",
      "change": "-1.46%",
      "dir": "neg"
    },
    {
      "sym": "WTI",
      "value": "$74.51",
      "change": "-2.97%",
      "dir": "neg"
    },
    {
      "sym": "GOLD",
      "value": "$4,284.90",
      "change": "-1.70%",
      "dir": "neg"
    },
    {
      "sym": "SILVER",
      "value": "$68.25",
      "change": "-3.47%",
      "dir": "neg"
    },
    {
      "sym": "COPPER",
      "value": "$6.40",
      "change": "-1.23%",
      "dir": "neg"
    },
    {
      "sym": "VIX",
      "value": "17.03",
      "change": "-7.65%",
      "dir": "neg"
    }
  ]
}